{
  "waterValveGridWidth": 200,
  "waterValveGridHeight": 100,
  "waterValveSpacingX": 0.25,
  "waterValveSpacingZ": 0.25,
  "waterValveBaseHeight": 9.0,
  "waterValveSize": 0.2,
  "valveControlImage": "pattern.bmp",

  "dropBurstInterval": 0.03,
  "dropMinSize": 0.05,
  "dropMaxSize": 0.09,
  "dropMinLife": 1.5,
  "dropMaxLife": 2.0,
  "dropSpeedYMin": -14.0,
  "dropSpeedYMax": -11.0,
  "gravity": -9.8,

  "poolWidth": 55.0,
  "poolDepth": 30.0,
  "waterColor": [ 0.2, 0.65, 0.95 ],
  "waterAlpha": 0.65
}